Metadata-Version: 1.1
Name: pyjstack
Version: 0.0.7
Summary: The pyjstack command-line tool for taking the thread dump
Home-page: http://github.com/sarathkumarsivan/pyjstack
Author: Sarath Kumar Sivan
Author-email: sarathkumarsivan@gmail.com
License: MIT
Keywords: pyjstack thread-dump
Platform: UNKNOWN
Classifier: Development Status :: 5 - Production/Stable
Classifier: Environment :: Console
Classifier: Intended Audience :: Developers
Classifier: License :: OSI Approved :: MIT License
Classifier: Natural Language :: English
Classifier: Programming Language :: Python :: 2.7
Classifier: Programming Language :: Python :: 3.4
Classifier: Programming Language :: Python :: 3.5
Classifier: Programming Language :: Python :: 3.6
